acestream_launcher/__init__.py
acestream_launcher/config.py
acestream_launcher/launcher.py
acestream_launcher/notify.py
acestream_launcher/player.py
acestream_launcher/stream.py
acestream_launcher-2.1.0.data/data/share/applications/acestream-launcher.desktop
acestream_launcher-2.1.0.dist-info/LICENSE.txt
acestream_launcher-2.1.0.dist-info/METADATA
acestream_launcher-2.1.0.dist-info/WHEEL
acestream_launcher-2.1.0.dist-info/entry_points.txt
acestream_launcher-2.1.0.dist-info/top_level.txt
acestream_launcher-2.1.0.dist-info/RECORD
