Metadata-Version: 2.1
Name: acestream-launcher
Version: 2.1.0
Summary: Open AceStream links with a Media Player of your choice
Home-page: https://github.com/jonian/acestream-launcher
Author: Jonian Guveli
Author-email: jonian@hardpixel.eu
License: UNKNOWN
Project-URL: Bug Reports, https://github.com/jonian/acestream-launcher/issues
Project-URL: Source, https://github.com/jonian/acestream-launcher
Platform: UNKNOWN
Classifier: Programming Language :: Python :: 2
Classifier: Programming Language :: Python :: 3
Classifier: License :: OSI Approved :: GNU General Public License v3 (GPLv3)
Classifier: Operating System :: POSIX :: Linux
Requires-Dist: acestream (>=0.2.0)
